{
  "accounts": [
    {
      "id": 1,
      "email": "test@example.com",
      "email_verification_status": "unspecified",
      "email_verification_token": "43a05e8a-f327-4a60-97fd-cef1f4b78420",
      "last_notification_read_at": "2019-08-24"
    }
  ],
  "profiles": [
    {
      "id": 1,
      "name": "甲斐義隆",
      "name_kana": "ヤマダタロウ",
      "gender": "MALE",
      "phone": "090-XXXX-XXXX",
      "postal_code": "107-0051",
      "address": "千葉県",
      "date_of_birth": "2019-08-24",
      "account_id": 1
    }
  ],
  "work_histories": [
    {
      "id": 1,
      "is_employed": "true",
      "occupation": {
        "id": 1,
        "name": "戦略・経営コンサルタント"
      },
      "industry": {
        "id": 1,
        "name": "銀行・信託銀行"
      },
      "position": "主任",
      "annual_income": 4000000,
      "management_experience": 3,
      "job_summary": "Ruby on Railsを使ったバックエンド開発",
      "since_date": "2019-08-01",
      "until_date": "2020-05-01",
      "name": "株式会社SIMULA Labs"
    }
  ],
  "academic_histories": [
    {
      "id": 1,
      "name": "明治大学",
      "faculty": "情報コミュニケーション学部",
      "since_date": "2008-04-01",
      "until_date": "2012-03-01",
      "type": "university"
    },
    {
      "name": "荏隈小学校",
      "faculty": "普通化",
      "since_date": "2021-10-25",
      "until_date": "2021-10-26",
      "id": 2
    }
  ],
  "companies": [
    {
      "name": "kkkkk",
      "name_kana": "kkkkkkkkkkk",
      "head_office_location": "sample1",
      "year_of_establishment": "1",
      "hp_url": "",
      "phone": "",
      "is_listed": "上場",
      "representative_last": "eeeeeeeee",
      "representative_first": "eeeeeeeee",
      "representative_kana_last": "eeeeeeeee",
      "representative_kana_first": "eeeeeeee",
      "net_sales": "",
      "numbers_of_employees": "",
      "average_age": "",
      "business_summery": "eeeeeeeeee",
      "corporate_pr": "",
      "logo_image": {},
      "id": 1
    },
    {
      "name": "ほげ",
      "name_kana": "ほげ",
      "head_office_location": "sample1",
      "year_of_establishment": "1",
      "hp_url": "hoge",
      "phone": "00000",
      "is_listed": "非上場",
      "representative_last": "ほげ",
      "representative_first": "ほげ",
      "representative_kana_last": "ほげ",
      "representative_kana_first": "ほげ",
      "net_sales": "1111",
      "numbers_of_employees": "",
      "average_age": "",
      "business_summary": "テスト",
      "corporate_pr": "",
      "logo_image": {},
      "id": 2
    },
    {
      "name": "ぎえ",
      "name_kana": "ほげ",
      "head_office_location": "sample2",
      "year_of_establishment": "1",
      "hp_url": "",
      "phone": "",
      "is_listed": "上場",
      "representative_last": "ほげ",
      "representative_first": "ほげ",
      "representative_kana_last": "ほげ",
      "representative_kana_first": "げほえ",
      "net_sales": "",
      "numbers_of_employees": "",
      "average_age": "",
      "business_summery": "ほげええええ",
      "corporate_pr": "",
      "logo_image": {},
      "id": 3
    },
    {
      "name": "お",
      "name_kana": "さえｆ",
      "head_office_location": "sample1",
      "year_of_establishment": "1",
      "hp_url": "",
      "phone": "",
      "is_listed": "上場",
      "representative_last": "ｄｆｓｄｆ",
      "representative_first": "ｄｆさ",
      "representative_kana_last": "ｆｇｓｇ",
      "representative_kana_first": "ｆｄｇ",
      "net_sales": "",
      "numbers_of_employees": "",
      "average_age": "",
      "business_summery": "ｇｆｄｓｇｆｄｓ",
      "corporate_pr": "",
      "logo_image": {},
      "id": 4
    }
  ]
}